.gitignore
.pre-commit-config.yaml
.pre-push-config.yaml
LICENSE.md
README.md
environment.yml
pyproject.toml
setup.cfg
setup.py
.github/workflows/flake8.yml
.github/workflows/pytest.yml
solo_sis_loader/__init__.py
solo_sis_loader/version.py
solo_sis_loader.egg-info/.DS_Store
solo_sis_loader.egg-info/PKG-INFO
solo_sis_loader.egg-info/SOURCES.txt
solo_sis_loader.egg-info/dependency_links.txt
solo_sis_loader.egg-info/not-zip-safe
solo_sis_loader.egg-info/requires.txt
solo_sis_loader.egg-info/top_level.txt
solo_sis_loader/test/__init__.py
solo_sis_loader/test/conftest.py
solo_sis_loader/test/solo_sis_loader_test.py