Metadata-Version: 2.2
Name: solo_sis_loader
Version: 0.2.0
Summary: SolO-SIS-Loader: A python data loader for Suprathermal Ion Spectrograph (SIS) instrument onboard Solar Orbiter (SolO).
Home-page: https://github.com/AthKouloumvakos/solo-sis-loader
Download-URL: https://pypi.org/project/solo-sis-loader
Author: Athanasios Kouloumvakos
Author-email: athkouloumvakos@gmail.com
License: GPL-3.0
Project-URL: Source Code, https://github.com/AthKouloumvakos/solo-sis-loader
Project-URL: Documentation, https://github.com/AthKouloumvakos/solo-sis-loader
Project-URL: Issue Tracker, https://github.com/AthKouloumvakos/solo-sis-loader/issues
Keywords: science,solar physics,solar,sun,solar energetic particles
Platform: any
Classifier: Development Status :: 4 - Beta
Classifier: Intended Audience :: Science/Research
Classifier: License :: OSI Approved :: GNU General Public License v3 (GPLv3)
Classifier: Natural Language :: English
Classifier: Operating System :: OS Independent
Classifier: Programming Language :: Python
Classifier: Programming Language :: Python :: 3
Classifier: Programming Language :: Python :: 3.8
Classifier: Programming Language :: Python :: 3.9
Classifier: Topic :: Scientific/Engineering :: Physics
Requires-Python: >=3.8
License-File: LICENSE.md
Requires-Dist: cdflib
Requires-Dist: numpy
Requires-Dist: sunpy[net]
Requires-Dist: sunpy-soar
Requires-Dist: xarray
Provides-Extra: test
Requires-Dist: pytest; extra == "test"
Requires-Dist: pytest-astropy; extra == "test"
Requires-Dist: pytest-sugar; extra == "test"
Dynamic: download-url
